mxc/__init__.py
mxc/cli.py
mxc-0.1.0.dist-info/LICENSE.txt
mxc-0.1.0.dist-info/METADATA
mxc-0.1.0.dist-info/WHEEL
mxc-0.1.0.dist-info/entry_points.txt
mxc-0.1.0.dist-info/top_level.txt
mxc-0.1.0.dist-info/RECORD
